{"dc_creator_sm": ["ML Infomap"], "dc_description_s": "Census wards for Kolkata, India", "dc_format_s": "Shapefile", "dc_publisher_s": "ML Infomap", "dc_rights_s": "Restricted", "dc_subject_sm": ["Administrative and political divisions", "Population", "Literacy", "Census data"], "dc_title_s": "India, Kolkata (Ward Census Data, 2001)", "dc_type_s": "Dataset", "dct_provenance_s": "MIT", "dct_spatial_sm": ["India--Kolkata"], "dct_references_s": "{\"http://www.opengis.net/def/serviceType/ogc/wms\": \"https://geodata.mit.edu/mitgeoserver/wms\", \"http://www.opengis.net/def/serviceType/ogc/wfs\": \"https://geodata.mit.edu/mitgeoserver/wfs\", \"http://www.opengis.net/cat/csw/csdgm\": \"https://geodata.mit.edu/metadata/SDE_DATA_IN_KOLKATA_F7WARD_2001.xml\"}", "layer_geom_type_s": "Polygon", "layer_id_s": "mit:SDE_DATA_IN_KOLKATA_F7WARD_2001", "layer_modified_dt": "2018-05-15T13:23:22Z", "layer_slug_s": "mit-pcusmxueejnlk", "solr_geom": "ENVELOPE(88.244789, 88.450310, 22.631611, 22.452484)", "geoblacklight_version": "1.0"}