{"dc_creator_sm": ["U.S. Environmental Protection Agency", "Federal Highway Administration, Office of Planning, HEPP-1", "Research and Innovative Technology Administration's Bureau of Transportation Statistics (RITA/BTS)"], "dc_description_s": "Non-attainment and maintenance areas for the United States and its territories.  For more detailed information on this dataset, see the Overview Description in the Entity Attribute section of this document.", "dc_format_s": "Shapefile", "dc_publisher_s": "Research and Innovative Technology Administration's Bureau of Transportation Statistics (RITA/BTS)", "dc_rights_s": "Public", "dc_subject_sm": ["Air quality"], "dc_title_s": "USA (Non-Attainment Areas: Particulate Matter 2.5, 2006)", "dc_type_s": "Dataset", "dct_provenance_s": "MIT", "dct_spatial_sm": ["United States"], "dct_references_s": "{\"http://www.opengis.net/def/serviceType/ogc/wms\": \"https://geodata.mit.edu/geoserver/wms\", \"http://www.opengis.net/def/serviceType/ogc/wfs\": \"https://geodata.mit.edu/geoserver/wfs\", \"http://www.opengis.net/cat/csw/csdgm\": \"https://geodata.mit.edu/metadata/SDE_DATA_US_N85PM25_2006.xml\"}", "layer_geom_type_s": "Polygon", "layer_id_s": "mit:SDE_DATA_US_N85PM25_2006", "layer_modified_dt": "2018-05-15T20:24:05Z", "layer_slug_s": "mit-oxmanzzx7nlo4", "solr_geom": "ENVELOPE(-121.587001, -71.856150, 48.475141, 32.660623)", "geoblacklight_version": "1.0"}