{"dc_creator_sm": ["Tele Atlas North America, Inc.", "ESRI"], "dc_description_s": "U.S. and Canada Rivers represents rivers and other linear water features within the United States and Canada.This data set provides six feature classes for displaying the data at different scales. Everything about the feature classes is the same but the level of generalization and its name. The base feature class is called <data set name> and isn't generalized. The least generalized feature class is called <data set name>_1, the next more generalized feature class is called <data set name>_2, and so on. For best performance, use the most appropriate feature class when displaying or printing.", "dc_format_s": "Shapefile", "dc_publisher_s": "Tele Atlas North America, Inc.", "dc_rights_s": "Restricted", "dc_subject_sm": ["Fresh water", "Water", "Hydrography", "Rivers", "Hydrology", "Drainage"], "dc_title_s": "Alaska (Rivers, 2010)", "dc_type_s": "Dataset", "dct_provenance_s": "MIT", "dct_spatial_sm": ["Alaska", "United States"], "dct_references_s": "{\"http://www.opengis.net/def/serviceType/ogc/wms\": \"https://geodata.mit.edu/mitgeoserver/wms\", \"http://www.opengis.net/def/serviceType/ogc/wfs\": \"https://geodata.mit.edu/mitgeoserver/wfs\", \"http://www.opengis.net/cat/csw/csdgm\": \"https://geodata.mit.edu/metadata/SDE_DATA_US_AK_P53RIVERS_2010.xml\"}", "layer_geom_type_s": "Line", "layer_id_s": "mit:SDE_DATA_US_AK_P53RIVERS_2010", "layer_modified_dt": "2018-05-15T19:08:35Z", "layer_slug_s": "mit-o2v46xxaorn42", "solr_geom": "ENVELOPE(-178.079805, 179.675162, 78.641631, 17.932051)", "geoblacklight_version": "1.0"}