{"dc_creator_sm": ["ML Infomap"], "dc_description_s": "Roads in Hyderabad, India.", "dc_format_s": "Shapefile", "dc_publisher_s": "ML Infomap", "dc_rights_s": "Restricted", "dc_subject_sm": ["Roads"], "dc_title_s": "India, Hyderabad (Roads, 2007)", "dc_type_s": "Dataset", "dct_provenance_s": "MIT", "dct_spatial_sm": ["India--Hyderabad"], "dct_references_s": "{\"http://www.opengis.net/def/serviceType/ogc/wms\": \"https://geodata.mit.edu/mitgeoserver/wms\", \"http://www.opengis.net/def/serviceType/ogc/wfs\": \"https://geodata.mit.edu/mitgeoserver/wfs\", \"http://www.opengis.net/cat/csw/csdgm\": \"https://geodata.mit.edu/metadata/SDE_DATA_IN_HYDERABAD_P2ROAD_2007.xml\"}", "layer_geom_type_s": "Line", "layer_id_s": "mit:SDE_DATA_IN_HYDERABAD_P2ROAD_2007", "layer_modified_dt": "2018-05-15T13:22:56Z", "layer_slug_s": "mit-j3dgv4k6g5pdc", "solr_geom": "ENVELOPE(78.315560, 78.626419, 17.547419, 17.251062)", "geoblacklight_version": "1.0"}