{"dc_creator_sm": ["City of Cambridge GIS"], "dc_description_s": "This layer provides a spatial representation of the all the T stations and emergency exits in the City of Cambridge.", "dc_format_s": "Shapefile", "dc_publisher_s": "Cambridge (MA) Geographic Information System (City of Cambridge GIS)", "dc_rights_s": "Restricted", "dc_subject_sm": ["Subway stations", "Railroad stations"], "dc_title_s": "Cambridge, MA (Train exits, 1995)", "dc_type_s": "Dataset", "dct_provenance_s": "MIT", "dct_spatial_sm": ["Massachusetts--Cambridge"], "dct_references_s": "{\"http://www.opengis.net/def/serviceType/ogc/wms\": \"https://geodata.mit.edu/mitgeoserver/wms\", \"http://www.opengis.net/def/serviceType/ogc/wfs\": \"https://geodata.mit.edu/mitgeoserver/wfs\", \"http://www.opengis.net/cat/csw/csdgm\": \"https://geodata.mit.edu/metadata/SDE_DATA_US_MA_CAMBRIDGE_P3EXITS_1995.xml\"}", "layer_geom_type_s": "Point", "layer_id_s": "mit:SDE_DATA_US_MA_CAMBRIDGE_P3EXITS_1995", "layer_modified_dt": "2018-05-15T19:57:18Z", "layer_slug_s": "mit-dvfn6l4xejpy4", "solr_geom": "ENVELOPE(-71.144415, -71.077374, 42.398926, 42.362185)", "geoblacklight_version": "1.0"}