{"dc_creator_sm": ["ML Infomap"], "dc_description_s": "Surface water in Hyderabad, India.", "dc_format_s": "Shapefile", "dc_publisher_s": "ML Infomap", "dc_rights_s": "Restricted", "dc_subject_sm": ["Canals", "Rivers", "Drainage", "Water"], "dc_title_s": "India, Hyderabad (Surface Water, 2007)", "dc_type_s": "Dataset", "dct_provenance_s": "MIT", "dct_spatial_sm": ["India--Hyderabad"], "dct_references_s": "{\"http://www.opengis.net/def/serviceType/ogc/wms\": \"https://geodata.mit.edu/mitgeoserver/wms\", \"http://www.opengis.net/def/serviceType/ogc/wfs\": \"https://geodata.mit.edu/mitgeoserver/wfs\", \"http://www.opengis.net/cat/csw/csdgm\": \"https://geodata.mit.edu/metadata/SDE_DATA_IN_HYDERABAD_C3WATER_2007.xml\"}", "layer_geom_type_s": "Polygon", "layer_id_s": "mit:SDE_DATA_IN_HYDERABAD_C3WATER_2007", "layer_modified_dt": "2018-05-15T13:22:49Z", "layer_slug_s": "mit-oliua6bkvnpam", "solr_geom": "ENVELOPE(78.300423, 78.623543, 17.544966, 17.302891)", "geoblacklight_version": "1.0"}