{"dc_creator_sm": ["U.S. Geological Society", "NASA Visible Earth Program", "NASA Earth Observatory", "SouthWestern Bell WorldRoom", "Bartholemew and Times Books", "NASA JSC Digital Image Collection", "Rand McNally & Company", "ESRI", "Defense Mapping Agency, presently known as National Imagery and Mapping Agency", "EROS Data Center of the U.S. Geological Survey"], "dc_description_s": "World Rivers represents the major rivers within the world.", "dc_format_s": "Shapefile", "dc_publisher_s": "EROS Data Center of the U.S. Geological Survey", "dc_rights_s": "Restricted", "dc_subject_sm": ["Lakes"], "dc_title_s": "World (Rivers, 2005)", "dc_type_s": "Dataset", "dct_provenance_s": "MIT", "dct_spatial_sm": ["Earth (Planet)"], "dct_references_s": "{\"http://www.opengis.net/def/serviceType/ogc/wms\": \"https://geodata.mit.edu/mitgeoserver/wms\", \"http://www.opengis.net/def/serviceType/ogc/wfs\": \"https://geodata.mit.edu/mitgeoserver/wfs\", \"http://www.opengis.net/cat/csw/csdgm\": \"https://geodata.mit.edu/metadata/SDE_DATA_INT_P53RIVERS_2005.xml\"}", "layer_geom_type_s": "Line", "layer_id_s": "mit:SDE_DATA_INT_P53RIVERS_2005", "layer_modified_dt": "2018-05-15T13:20:26Z", "layer_slug_s": "mit-cywxaqxfbjkjk", "solr_geom": "ENVELOPE(-164.887436, 160.763596, 71.392490, -36.969445)", "geoblacklight_version": "1.0"}