{"dc_creator_sm": ["U.S. Geological Survey in cooperation with U.S. Environmental Protection Agency", "ESRI"], "dc_description_s": "U.S. Water Bodies represents the major lakes, reservoirs, large rivers, lagoons, and estuaries in the United States.", "dc_format_s": "Shapefile", "dc_publisher_s": "U.S. Geological Survey", "dc_rights_s": "Restricted", "dc_subject_sm": ["Water"], "dc_title_s": "USA (Water Bodies, 2005)", "dc_type_s": "Dataset", "dct_provenance_s": "MIT", "dct_spatial_sm": ["United States"], "dct_references_s": "{\"http://www.opengis.net/def/serviceType/ogc/wms\": \"https://geodata.mit.edu/mitgeoserver/wms\", \"http://www.opengis.net/def/serviceType/ogc/wfs\": \"https://geodata.mit.edu/mitgeoserver/wfs\", \"http://www.opengis.net/cat/csw/csdgm\": \"https://geodata.mit.edu/metadata/SDE_DATA_US_C3WAT_2005.xml\"}", "layer_geom_type_s": "Polygon", "layer_id_s": "mit:SDE_DATA_US_C3WAT_2005", "layer_modified_dt": "2018-05-15T19:12:48Z", "layer_slug_s": "mit-my6srksfvzif4", "solr_geom": "ENVELOPE(-160.231107, -66.997867, 49.384333, 19.203998)", "geoblacklight_version": "1.0"}